MANIFEST.in
README.md
requirements-min-django.txt
requirements-test.txt
requirements.txt
setup.py
chosen/__init__.py
chosen/fields.py
chosen/forms.py
chosen/widgets.py
chosen/static/chosen/css/chosen-sprite.png
chosen/static/chosen/css/chosen-sprite@2x.png
chosen/static/chosen/css/chosen.css
chosen/static/chosen/js/chosen.LICENSE.md
chosen/static/chosen/js/chosen.jquery.js
chosen/static/chosen/js/chosen.jquery.min.js
chosen/static/chosen/js/chosen.jquery_ready.js
django_chosen_mega.egg-info/PKG-INFO
django_chosen_mega.egg-info/SOURCES.txt
django_chosen_mega.egg-info/dependency_links.txt
django_chosen_mega.egg-info/not-zip-safe
django_chosen_mega.egg-info/requires.txt
django_chosen_mega.egg-info/top_level.txt