Metadata-Version: 1.1
Name: django-chosen-mega
Version: 0.1.5
Summary: django FormFields using the Chosen javascript plugin for jQuery
Home-page: https://github.com/chrisspen/django-chosen
Author: Chris Spencer
Author-email: chrisspen@gmail.com
License: UNKNOWN
Platform: UNKNOWN
Classifier: Environment :: Web Environment
Classifier: Intended Audience :: Developers
Classifier: Operating System :: OS Independent
Classifier: Programming Language :: Python
Classifier: Programming Language :: Python :: 3
Classifier: Programming Language :: Python :: 3.4
Classifier: Programming Language :: Python :: 3.6
Classifier: Framework :: Django
